mousetumornet/__init__.py
mousetumornet/cli.py
mousetumornet/configuration.py
mousetumornet/napari.yaml
mousetumornet/nnunet_predict.py
mousetumornet/roi.py
mousetumornet/roi_widget.py
mousetumornet/napari_nnunet/__init__.py
mousetumornet/napari_nnunet/nnunet_widget.py
mousetumornet-0.0.6.dist-info/LICENSE
mousetumornet-0.0.6.dist-info/METADATA
mousetumornet-0.0.6.dist-info/WHEEL
mousetumornet-0.0.6.dist-info/entry_points.txt
mousetumornet-0.0.6.dist-info/top_level.txt
mousetumornet-0.0.6.dist-info/RECORD
