Metadata-Version: 2.1
Name: mousetumornet
Version: 0.0.6
Summary: nnU-Net model for the segmentation of lung tumor nodules in mice CT scans.
Home-page: https://gitlab.epfl.ch/center-for-imaging/mousetumornet.git
Author: Center for Imaging, Ecole Polytechnique Federale de Lausanne (EPFL)
Author-email: mallory.wittwer@epfl.ch
License: BSD-3-Clause
Project-URL: Source Code, https://gitlab.epfl.ch/center-for-imaging/mousetumornet.git
Classifier: Development Status :: 2 - Pre-Alpha
Classifier: Intended Audience :: Developers
Classifier: License :: OSI Approved :: BSD License
Classifier: Operating System :: OS Independent
Classifier: Programming Language :: Python
Classifier: Programming Language :: Python :: 3
Classifier: Programming Language :: Python :: 3 :: Only
Classifier: Programming Language :: Python :: 3.8
Classifier: Programming Language :: Python :: 3.9
Classifier: Programming Language :: Python :: 3.10
Classifier: Topic :: Scientific/Engineering :: Image Processing
Requires-Python: >=3.8
License-File: LICENSE
Requires-Dist: magicgui
Requires-Dist: qtpy
Requires-Dist: napari[all]>=0.4.16
Requires-Dist: napari-label-focus
Requires-Dist: pooch
Requires-Dist: nnunetv2
Provides-Extra: testing
Requires-Dist: tox; extra == "testing"
Requires-Dist: pytest; extra == "testing"
Requires-Dist: pytest-cov; extra == "testing"
Requires-Dist: pytest-qt; extra == "testing"
Requires-Dist: napari; extra == "testing"
Requires-Dist: pyqt5; extra == "testing"
